{
  "updated": "2026-07-24T00:31:28Z",
  "vessels": [
    {
      "mmsi": 367050160,
      "name": "BURNS HARBOR",
      "type": 70,
      "lat": 46.69989,
      "lon": -92.01853,
      "sog": 0,
      "cog": 0,
      "heading": 180,
      "length": 304,
      "beam": 32,
      "destination": "SUPERIOR WI",
      "lastReport": "2026-07-24T00:30:25Z"
    },
    {
      "mmsi": 366983440,
      "name": "JOYCE L VANENKEVORT",
      "type": 52,
      "lat": 42.70956,
      "lon": -82.49312,
      "sog": 10.7,
      "cog": 205,
      "heading": 202,
      "length": 257,
      "beam": 23,
      "destination": "TOLEDO",
      "lastReport": "2026-07-24T00:30:43Z"
    },
    {
      "mmsi": 366904890,
      "name": "HON JAMES L OBERSTAR",
      "type": 70,
      "lat": 45.69403,
      "lon": -86.07668,
      "sog": 11.8,
      "cog": 241,
      "heading": 243,
      "length": 246,
      "beam": 24,
      "destination": "BURNS HARBOR",
      "lastReport": "2026-07-24T00:30:18Z"
    },
    {
      "mmsi": 316001633,
      "name": "CSL ASSINIBOINE",
      "type": 70,
      "lat": 46.73223,
      "lon": -91.99559,
      "sog": 0,
      "cog": 357,
      "heading": 197,
      "length": 226,
      "beam": 24,
      "destination": "SUPERIOR WI",
      "lastReport": "2026-07-24T00:30:52Z"
    },
    {
      "mmsi": 316026695,
      "name": "CSL WELLAND",
      "type": 70,
      "lat": 42.69791,
      "lon": -79.60511,
      "sog": 12,
      "cog": 238,
      "heading": 239,
      "length": 226,
      "beam": 24,
      "destination": "MONTREAL",
      "lastReport": "2026-07-24T00:30:56Z"
    },
    {
      "mmsi": 316001844,
      "name": "SPRUCEGLEN",
      "type": 70,
      "lat": 42.97729,
      "lon": -79.22125,
      "sog": 7.7,
      "cog": 197,
      "heading": 196,
      "length": 223,
      "beam": 24,
      "destination": "THUNDER BAY",
      "lastReport": "2026-07-24T00:31:23Z"
    },
    {
      "mmsi": 366938710,
      "name": "AMERICAN MARINER",
      "type": 70,
      "lat": 48.44777,
      "lon": -89.18208,
      "sog": 0,
      "cog": 342,
      "heading": 342,
      "length": 222,
      "beam": 23,
      "destination": "DULUTH",
      "lastReport": "2026-07-24T00:30:59Z"
    },
    {
      "mmsi": 316001701,
      "name": "JOHN D LEITCH",
      "type": 70,
      "lat": 43.27439,
      "lon": -79.79805,
      "sog": 0,
      "cog": 49,
      "heading": 198,
      "length": 222,
      "beam": 24,
      "destination": "HAMILTON",
      "lastReport": "2026-07-24T00:31:17Z"
    },
    {
      "mmsi": 366938770,
      "name": "H LEE WHITE",
      "type": 70,
      "lat": 42.19344,
      "lon": -83.13387,
      "sog": 9.9,
      "cog": 184,
      "heading": 183,
      "length": 215,
      "beam": 24,
      "destination": "DULUTH",
      "lastReport": "2026-07-24T00:30:44Z"
    },
    {
      "mmsi": 316059017,
      "name": "ONTARIO VENTURE",
      "type": 70,
      "lat": 42.28927,
      "lon": -83.14115,
      "sog": 0,
      "cog": 127,
      "heading": 337,
      "length": 207,
      "beam": 24,
      "destination": "DETROIT CH 69",
      "lastReport": "2026-07-24T00:30:56Z"
    },
    {
      "mmsi": 316035905,
      "name": "ALGOMA INNOVATOR",
      "type": 70,
      "lat": 43.24281,
      "lon": -82.26601,
      "sog": 13.6,
      "cog": 35,
      "heading": 34,
      "length": 198,
      "beam": 24,
      "destination": "GODERICH",
      "lastReport": "2026-07-24T00:31:07Z"
    },
    {
      "mmsi": 367341010,
      "name": "MANITOWOC",
      "type": 70,
      "lat": 42.92311,
      "lon": -82.45988,
      "sog": 0,
      "cog": 356,
      "heading": 14,
      "length": 192,
      "beam": 21,
      "destination": "CALCITE",
      "lastReport": "2026-07-24T00:31:19Z"
    },
    {
      "mmsi": 212372000,
      "name": "BRANT",
      "type": 70,
      "lat": 43.15584,
      "lon": -79.19373,
      "sog": 0,
      "cog": 171,
      "heading": 174,
      "length": 185,
      "beam": 24,
      "destination": "CA THU",
      "lastReport": "2026-07-24T00:31:20Z"
    },
    {
      "mmsi": 316053441,
      "name": "ALGOLUNA",
      "type": 89,
      "lat": 42.81696,
      "lon": -79.25213,
      "sog": 3.2,
      "cog": 339,
      "heading": 340,
      "length": 144,
      "beam": 23,
      "destination": "QUEBEC",
      "lastReport": "2026-07-24T00:31:11Z"
    },
    {
      "mmsi": 255915987,
      "name": "STENHEIM",
      "type": 80,
      "lat": 41.98752,
      "lon": -83.1321,
      "sog": 11.5,
      "cog": 344,
      "heading": 344,
      "length": 144,
      "beam": 23,
      "destination": "US DET",
      "lastReport": "2026-07-24T00:30:36Z"
    },
    {
      "mmsi": 316040257,
      "name": "HINCH SPIRIT",
      "type": 89,
      "lat": 43.29582,
      "lon": -79.83661,
      "sog": 0.1,
      "cog": 192,
      "heading": 248,
      "length": 137,
      "beam": 20,
      "destination": "CAHAM",
      "lastReport": "2026-07-24T00:31:17Z"
    }
  ]
}