{
  "updated": "2026-07-16T03:16:29Z",
  "vessels": [
    {
      "mmsi": 367050160,
      "name": "BURNS HARBOR",
      "type": 70,
      "lat": 46.69986,
      "lon": -92.01858,
      "sog": 0,
      "cog": 189,
      "heading": 180,
      "length": 304,
      "beam": 32,
      "destination": "SUPERIOR",
      "lastReport": "2026-07-16T03:15:31Z"
    },
    {
      "mmsi": 316026694,
      "name": "CSL ST-LAURENT",
      "type": 70,
      "lat": 48.41416,
      "lon": -89.22163,
      "sog": 0,
      "cog": 273,
      "heading": 270,
      "length": 226,
      "beam": 24,
      "destination": "THUNDER BAY",
      "lastReport": "2026-07-16T03:15:35Z"
    },
    {
      "mmsi": 316001637,
      "name": "CSL LAURENTIEN",
      "type": 79,
      "lat": 46.75084,
      "lon": -92.13387,
      "sog": 0,
      "cog": 58,
      "heading": 317,
      "length": 225,
      "beam": 24,
      "destination": "TWO HARBORS",
      "lastReport": "2026-07-16T03:15:37Z"
    },
    {
      "mmsi": 316009090,
      "name": "ALGOMA EQUINOX",
      "type": 70,
      "lat": 43.30209,
      "lon": -79.78963,
      "sog": 7,
      "cog": 235,
      "heading": 236,
      "length": 224,
      "beam": 24,
      "destination": "HAMILTON",
      "lastReport": "2026-07-16T03:16:21Z"
    },
    {
      "mmsi": 316001844,
      "name": "SPRUCEGLEN",
      "type": 70,
      "lat": 44.70014,
      "lon": -82.78753,
      "sog": 13,
      "cog": 163,
      "heading": 164,
      "length": 223,
      "beam": 24,
      "destination": "SOREL",
      "lastReport": "2026-07-16T03:15:36Z"
    },
    {
      "mmsi": 316014160,
      "name": "MANITOULIN",
      "type": 70,
      "lat": 42.28489,
      "lon": -83.13867,
      "sog": 0.1,
      "cog": 204,
      "heading": 349,
      "length": 203,
      "beam": 24,
      "destination": "DRUMMOND CH.69",
      "lastReport": "2026-07-16T03:16:09Z"
    },
    {
      "mmsi": 538011029,
      "name": "HURON",
      "type": 80,
      "lat": 42.90569,
      "lon": -82.45881,
      "sog": 0,
      "cog": 127,
      "heading": 13,
      "length": 157,
      "beam": 23,
      "destination": "CAMNT->CASNI",
      "lastReport": "2026-07-16T03:15:57Z"
    },
    {
      "mmsi": 366893910,
      "name": "ALPENA",
      "type": 70,
      "lat": 43.4158,
      "lon": -87.50042,
      "sog": 12.3,
      "cog": 33,
      "heading": 33,
      "length": 153,
      "beam": 20,
      "destination": "ALPENA",
      "lastReport": "2026-07-16T03:15:54Z"
    },
    {
      "mmsi": 316013946,
      "name": "LEO A.MCARTHUR",
      "type": 80,
      "lat": 43.29606,
      "lon": -79.82926,
      "sog": 0,
      "cog": 98,
      "heading": 235,
      "length": 152,
      "beam": 22,
      "destination": "OSHAWA",
      "lastReport": "2026-07-16T03:15:17Z"
    },
    {
      "mmsi": 255915987,
      "name": "STENHEIM",
      "type": 80,
      "lat": 43.2717,
      "lon": -79.84596,
      "sog": 0,
      "cog": 204,
      "heading": 17,
      "length": 144,
      "beam": 23,
      "destination": "CA HAM",
      "lastReport": "2026-07-16T03:15:56Z"
    },
    {
      "mmsi": 316050854,
      "name": "ALGOTITAN",
      "type": 80,
      "lat": 43.50658,
      "lon": -78.26502,
      "sog": 11.5,
      "cog": 74,
      "heading": 73,
      "length": 143,
      "beam": 23,
      "destination": "SARNIA",
      "lastReport": "2026-07-16T03:16:18Z"
    }
  ]
}