{
  "updated": "2026-07-02T15:16:37Z",
  "vessels": [
    {
      "mmsi": 366904880,
      "name": "MESABI MINER",
      "type": 70,
      "lat": 47.52941,
      "lon": -88.42333,
      "sog": 12.6,
      "cog": 82,
      "heading": 80,
      "length": 305,
      "beam": 32,
      "destination": "CLEVELAND",
      "lastReport": "2026-07-02T15:16:27Z"
    },
    {
      "mmsi": 367050160,
      "name": "BURNS HARBOR",
      "type": 70,
      "lat": 47.35727,
      "lon": -89.55089,
      "sog": 12.4,
      "cog": 78,
      "heading": 77,
      "length": 304,
      "beam": 32,
      "destination": "SUPERIOR",
      "lastReport": "2026-07-02T15:15:53Z"
    },
    {
      "mmsi": 316026694,
      "name": "CSL ST-LAURENT",
      "type": 70,
      "lat": 48.41416,
      "lon": -89.22052,
      "sog": 0,
      "cog": 359,
      "heading": 271,
      "length": 226,
      "beam": 24,
      "destination": "THUNDER BAY",
      "lastReport": "2026-07-02T15:15:31Z"
    },
    {
      "mmsi": 316001844,
      "name": "SPRUCEGLEN",
      "type": 70,
      "lat": 44.21866,
      "lon": -76.17923,
      "sog": 13.2,
      "cog": 65,
      "heading": 65,
      "length": 223,
      "beam": 24,
      "destination": "SOREL SEC 14",
      "lastReport": "2026-07-02T15:15:46Z"
    },
    {
      "mmsi": 316018031,
      "name": "ALGOMA GUARDIAN",
      "type": 70,
      "lat": 43.28,
      "lon": -79.80215,
      "sog": 0,
      "cog": 84,
      "heading": 107,
      "length": 222,
      "beam": 23,
      "destination": "HAMILTON",
      "lastReport": "2026-07-02T15:16:02Z"
    },
    {
      "mmsi": 316036229,
      "name": "ALGOMA COMPASS",
      "type": 70,
      "lat": 43.27908,
      "lon": -79.79188,
      "sog": 0,
      "cog": 98,
      "heading": 149,
      "length": 207,
      "beam": 24,
      "destination": "GODERICH",
      "lastReport": "2026-07-02T15:15:30Z"
    },
    {
      "mmsi": 316011905,
      "name": "ROBERT S. PIERSON",
      "type": 70,
      "lat": 42.91421,
      "lon": -82.46049,
      "sog": 9.4,
      "cog": 195,
      "heading": 196,
      "length": 192,
      "beam": 21,
      "destination": "WINDSOR CH 69",
      "lastReport": "2026-07-02T15:15:43Z"
    },
    {
      "mmsi": 209016000,
      "name": "TORRENT",
      "type": 70,
      "lat": 43.64226,
      "lon": -79.36811,
      "sog": 0,
      "cog": 336,
      "heading": 333,
      "length": 185,
      "beam": 24,
      "destination": "CA TOR",
      "lastReport": "2026-07-02T15:16:01Z"
    },
    {
      "mmsi": 316003878,
      "name": "WILF SEYMOUR",
      "type": 52,
      "lat": 44.20607,
      "lon": -76.22581,
      "sog": 9.5,
      "cog": 247,
      "heading": 246,
      "length": 159,
      "beam": 24,
      "destination": "TOLEDO",
      "lastReport": "2026-07-02T15:16:15Z"
    },
    {
      "mmsi": 305594000,
      "name": "BBC KOLDING",
      "type": 70,
      "lat": 43.15467,
      "lon": -79.1936,
      "sog": 0,
      "cog": 173,
      "heading": 173,
      "length": 149,
      "beam": 23,
      "destination": "THUNDERBAY",
      "lastReport": "2026-07-02T15:15:23Z"
    },
    {
      "mmsi": 316036419,
      "name": "MCKEIL SPIRIT",
      "type": 70,
      "lat": 43.65306,
      "lon": -79.32687,
      "sog": 0,
      "cog": 31,
      "heading": 67,
      "length": 140,
      "beam": 21,
      "destination": "TORONTO",
      "lastReport": "2026-07-02T15:16:26Z"
    },
    {
      "mmsi": 244283000,
      "name": "IVER BRIGHT",
      "type": 89,
      "lat": 42.93404,
      "lon": -82.44711,
      "sog": 0,
      "cog": 186,
      "heading": 31,
      "length": 110,
      "beam": 18,
      "destination": "CASNI",
      "lastReport": "2026-07-02T15:15:31Z"
    }
  ]
}