{
  "updated": "2026-07-15T04:31:43Z",
  "vessels": [
    {
      "mmsi": 367120990,
      "name": "AMERICAN INTEGRITY",
      "type": 70,
      "lat": 43.09024,
      "lon": -82.41165,
      "sog": 9.9,
      "cog": 7,
      "heading": 15,
      "length": 305,
      "beam": 32,
      "destination": "CONNEAUT",
      "lastReport": "2026-07-15T04:31:22Z"
    },
    {
      "mmsi": 316011710,
      "name": "ALGOMA HARVESTER",
      "type": 70,
      "lat": 43.19369,
      "lon": -79.20289,
      "sog": 0,
      "cog": 209,
      "heading": 156,
      "length": 225,
      "beam": 24,
      "destination": "SUPERIOR",
      "lastReport": "2026-07-15T04:31:20Z"
    },
    {
      "mmsi": 316023808,
      "name": "BAIE COMEAU",
      "type": 70,
      "lat": 43.30237,
      "lon": -79.58228,
      "sog": 12.5,
      "cog": 97,
      "heading": 98,
      "length": 225,
      "beam": 24,
      "destination": "TOLEDO",
      "lastReport": "2026-07-15T04:31:00Z"
    },
    {
      "mmsi": 316001834,
      "name": "FRONTENAC",
      "type": 70,
      "lat": 42.88208,
      "lon": -79.24826,
      "sog": 0,
      "cog": 196,
      "heading": 0,
      "length": 223,
      "beam": 23,
      "destination": "HAMILTON PIER 23",
      "lastReport": "2026-07-15T04:31:39Z"
    },
    {
      "mmsi": 316009457,
      "name": "KAMINISTIQUA",
      "type": 70,
      "lat": 42.01808,
      "lon": -81.75057,
      "sog": 11.8,
      "cog": 248,
      "heading": 248,
      "length": 223,
      "beam": 23,
      "destination": "THUNDER BAY",
      "lastReport": "2026-07-15T04:30:33Z"
    },
    {
      "mmsi": 538006434,
      "name": "FEDERAL BISCAY",
      "type": 70,
      "lat": 48.44451,
      "lon": -89.18601,
      "sog": 0.8,
      "cog": 314,
      "heading": 323,
      "length": 200,
      "beam": 24,
      "destination": "THUNDERBAY",
      "lastReport": "2026-07-15T04:31:18Z"
    },
    {
      "mmsi": 316043882,
      "name": "ALGOMA INTREPID",
      "type": 70,
      "lat": 42.31048,
      "lon": -83.07628,
      "sog": 6.4,
      "cog": 40,
      "heading": 49,
      "length": 198,
      "beam": 24,
      "destination": "ESSEXVILLE",
      "lastReport": "2026-07-15T04:30:28Z"
    },
    {
      "mmsi": 367121040,
      "name": "AMERICAN COURAGE",
      "type": 70,
      "lat": 41.5056,
      "lon": -81.71312,
      "sog": 0.7,
      "cog": 224,
      "heading": 54,
      "length": 194,
      "beam": 21,
      "destination": "CLEVELAND",
      "lastReport": "2026-07-15T04:31:17Z"
    },
    {
      "mmsi": 316006868,
      "name": "KATHY MCKEIL",
      "type": 70,
      "lat": 42.30165,
      "lon": -83.08983,
      "sog": 0,
      "cog": 262,
      "heading": 35,
      "length": 179,
      "beam": 23,
      "destination": "TOLEDO",
      "lastReport": "2026-07-15T04:30:54Z"
    },
    {
      "mmsi": 316003878,
      "name": "WILF SEYMOUR",
      "type": 52,
      "lat": 43.37238,
      "lon": -78.90395,
      "sog": 9.5,
      "cog": 75,
      "heading": 74,
      "length": 159,
      "beam": 24,
      "destination": "MONTREAL 43N",
      "lastReport": "2026-07-15T04:30:45Z"
    },
    {
      "mmsi": 316053441,
      "name": "ALGOLUNA",
      "type": 89,
      "lat": 42.79134,
      "lon": -80.04121,
      "sog": 7,
      "cog": 178,
      "heading": 189,
      "length": 144,
      "beam": 23,
      "destination": "NANTICOKE",
      "lastReport": "2026-07-15T04:30:57Z"
    },
    {
      "mmsi": 255915987,
      "name": "STENHEIM",
      "type": 80,
      "lat": 43.27169,
      "lon": -79.84597,
      "sog": 0,
      "cog": 204,
      "heading": 18,
      "length": 144,
      "beam": 23,
      "destination": "CA HAM",
      "lastReport": "2026-07-15T04:30:28Z"
    },
    {
      "mmsi": 244283000,
      "name": "IVER BRIGHT",
      "type": 89,
      "lat": 43.46669,
      "lon": -77.78494,
      "sog": 8.3,
      "cog": 89,
      "heading": 87,
      "length": 110,
      "beam": 18,
      "destination": "US OSW",
      "lastReport": "2026-07-15T04:31:12Z"
    }
  ]
}