{
  "updated": "2026-07-05T17:49:41Z",
  "vessels": [
    {
      "mmsi": 366983440,
      "name": "JOYCE L VANENKEVORT",
      "type": 52,
      "lat": 42.30186,
      "lon": -83.0896,
      "sog": 0,
      "cog": 30,
      "heading": 38,
      "length": 257,
      "beam": 23,
      "destination": "BREVORT",
      "lastReport": "2026-07-05T17:48:53Z"
    },
    {
      "mmsi": 316001633,
      "name": "CSL ASSINIBOINE",
      "type": 70,
      "lat": 42.15346,
      "lon": -83.12834,
      "sog": 9.5,
      "cog": 343,
      "heading": 343,
      "length": 226,
      "beam": 24,
      "destination": "HAMILTON",
      "lastReport": "2026-07-05T17:48:53Z"
    },
    {
      "mmsi": 316001836,
      "name": "CSL TADOUSSAC",
      "type": 70,
      "lat": 43.48506,
      "lon": -79.61075,
      "sog": 0,
      "cog": 264,
      "heading": 315,
      "length": 223,
      "beam": 23,
      "destination": "CLARKSON",
      "lastReport": "2026-07-05T17:48:53Z"
    },
    {
      "mmsi": 316018031,
      "name": "ALGOMA GUARDIAN",
      "type": 70,
      "lat": 43.27521,
      "lon": -79.78848,
      "sog": 0,
      "cog": 68,
      "heading": 329,
      "length": 222,
      "beam": 23,
      "destination": "HAMILTON",
      "lastReport": "2026-07-05T17:48:56Z"
    },
    {
      "mmsi": 538006469,
      "name": "FEDERAL CHURCHILL",
      "type": 70,
      "lat": 46.75217,
      "lon": -92.09647,
      "sog": 0,
      "cog": 166,
      "heading": 242,
      "length": 200,
      "beam": 23,
      "destination": "US DLH",
      "lastReport": "2026-07-05T17:48:52Z"
    },
    {
      "mmsi": 538010777,
      "name": "FEDERAL THUNDER BAY",
      "type": 70,
      "lat": 48.36869,
      "lon": -89.23788,
      "sog": 0,
      "cog": 352,
      "heading": 120,
      "length": 200,
      "beam": 24,
      "destination": "CATHU",
      "lastReport": "2026-07-05T17:48:48Z"
    },
    {
      "mmsi": 316036228,
      "name": "ALGOMA BUFFALO",
      "type": 70,
      "lat": 42.74546,
      "lon": -79.50303,
      "sog": 12.5,
      "cog": 241,
      "heading": 240,
      "length": 194,
      "beam": 21,
      "destination": "GODERICH",
      "lastReport": "2026-07-05T17:49:28Z"
    },
    {
      "mmsi": 266463000,
      "name": "THUN VENERN",
      "type": 80,
      "lat": 43.26864,
      "lon": -79.27955,
      "sog": 12.5,
      "cog": 288,
      "heading": 287,
      "length": 150,
      "beam": 23,
      "destination": "CA OAK",
      "lastReport": "2026-07-05T17:48:28Z"
    },
    {
      "mmsi": 316017550,
      "name": "MCASPHALT ADVANTAGE",
      "type": 80,
      "lat": 42.79805,
      "lon": -80.04336,
      "sog": 0,
      "cog": 344,
      "heading": 161,
      "length": 140,
      "beam": 24,
      "destination": "NANTICOKE",
      "lastReport": "2026-07-05T17:48:29Z"
    },
    {
      "mmsi": 316041965,
      "name": "TAMARACK",
      "type": 70,
      "lat": 43.21695,
      "lon": -79.21324,
      "sog": 0,
      "cog": 345,
      "heading": 343,
      "length": 123,
      "beam": 23,
      "destination": "BATH,ON",
      "lastReport": "2026-07-05T17:49:36Z"
    }
  ]
}