{
  "updated": "2026-07-05T19:13:44Z",
  "vessels": [
    {
      "mmsi": 366971370,
      "name": "EDWIN H. GOTT",
      "type": 70,
      "lat": 42.78375,
      "lon": -80.07686,
      "sog": 0,
      "cog": 316,
      "heading": 165,
      "length": 305,
      "beam": 32,
      "destination": "SUPERIOR",
      "lastReport": "2026-07-05T19:12:52Z"
    },
    {
      "mmsi": 316001633,
      "name": "CSL ASSINIBOINE",
      "type": 70,
      "lat": 42.32729,
      "lon": -83.02286,
      "sog": 9.7,
      "cog": 71,
      "heading": 71,
      "length": 226,
      "beam": 24,
      "destination": "HAMILTON",
      "lastReport": "2026-07-05T19:13:32Z"
    },
    {
      "mmsi": 316009090,
      "name": "ALGOMA EQUINOX",
      "type": 70,
      "lat": 42.36615,
      "lon": -82.89873,
      "sog": 11.6,
      "cog": 233,
      "heading": 237,
      "length": 224,
      "beam": 24,
      "destination": "QUEBEC CITY",
      "lastReport": "2026-07-05T19:13:30Z"
    },
    {
      "mmsi": 316018031,
      "name": "ALGOMA GUARDIAN",
      "type": 70,
      "lat": 43.2752,
      "lon": -79.78847,
      "sog": 0,
      "cog": 279,
      "heading": 329,
      "length": 222,
      "beam": 23,
      "destination": "HAMILTON",
      "lastReport": "2026-07-05T19:12:56Z"
    },
    {
      "mmsi": 538006469,
      "name": "FEDERAL CHURCHILL",
      "type": 70,
      "lat": 46.75217,
      "lon": -92.09647,
      "sog": 0.1,
      "cog": 199,
      "heading": 242,
      "length": 200,
      "beam": 23,
      "destination": "US DLH",
      "lastReport": "2026-07-05T19:12:52Z"
    },
    {
      "mmsi": 538010777,
      "name": "FEDERAL THUNDER BAY",
      "type": 70,
      "lat": 48.36872,
      "lon": -89.23788,
      "sog": 0,
      "cog": 352,
      "heading": 121,
      "length": 200,
      "beam": 24,
      "destination": "CATHU",
      "lastReport": "2026-07-05T19:12:48Z"
    },
    {
      "mmsi": 255916529,
      "name": "POLSTEAM WIGRY",
      "type": 70,
      "lat": 47.97691,
      "lon": -87.74503,
      "sog": 12.8,
      "cog": 300,
      "heading": 299,
      "length": 200,
      "beam": 24,
      "destination": "CA THU",
      "lastReport": "2026-07-05T19:13:24Z"
    },
    {
      "mmsi": 316036228,
      "name": "ALGOMA BUFFALO",
      "type": 70,
      "lat": 42.59437,
      "lon": -79.8422,
      "sog": 12.5,
      "cog": 240,
      "heading": 238,
      "length": 194,
      "beam": 21,
      "destination": "GODERICH",
      "lastReport": "2026-07-05T19:13:34Z"
    },
    {
      "mmsi": 367341010,
      "name": "MANITOWOC",
      "type": 70,
      "lat": 42.98282,
      "lon": -82.41908,
      "sog": 9.9,
      "cog": 152,
      "heading": 156,
      "length": 192,
      "beam": 21,
      "destination": "DETROIT",
      "lastReport": "2026-07-05T19:13:33Z"
    },
    {
      "mmsi": 636024470,
      "name": "GOLDEN PALM",
      "type": 80,
      "lat": 42.95922,
      "lon": -82.41871,
      "sog": 0,
      "cog": 118,
      "heading": 36,
      "length": 150,
      "beam": 23,
      "destination": "CASNI",
      "lastReport": "2026-07-05T19:13:03Z"
    },
    {
      "mmsi": 266463000,
      "name": "THUN VENERN",
      "type": 80,
      "lat": 43.35668,
      "lon": -79.65477,
      "sog": 12.2,
      "cog": 285,
      "heading": 284,
      "length": 150,
      "beam": 23,
      "destination": "CA OAK",
      "lastReport": "2026-07-05T19:13:39Z"
    },
    {
      "mmsi": 316055401,
      "name": "ALGOSOLIS",
      "type": 82,
      "lat": 42.84131,
      "lon": -79.2651,
      "sog": 9.2,
      "cog": 28,
      "heading": 26,
      "length": 144,
      "beam": 23,
      "destination": "DARTMOUTH NS",
      "lastReport": "2026-07-05T19:13:19Z"
    },
    {
      "mmsi": 316051091,
      "name": "ALGOBERTA",
      "type": 80,
      "lat": 42.90835,
      "lon": -79.24365,
      "sog": 0,
      "cog": 197,
      "heading": 189,
      "length": 143,
      "beam": 23,
      "destination": "CANAN",
      "lastReport": "2026-07-05T19:13:36Z"
    },
    {
      "mmsi": 316013215,
      "name": "ALGOCANADA",
      "type": 81,
      "lat": 44.19268,
      "lon": -76.30841,
      "sog": 12,
      "cog": 40,
      "heading": 47,
      "length": 130,
      "beam": 20,
      "destination": "MONTREAL",
      "lastReport": "2026-07-05T19:12:45Z"
    },
    {
      "mmsi": 316041965,
      "name": "TAMARACK",
      "type": 70,
      "lat": 43.32366,
      "lon": -79.10607,
      "sog": 9.7,
      "cog": 49,
      "heading": 53,
      "length": 123,
      "beam": 23,
      "destination": "BATH,ON",
      "lastReport": "2026-07-05T19:12:34Z"
    }
  ]
}