{
  "updated": "2026-07-08T18:01:55Z",
  "vessels": [
    {
      "mmsi": 366904940,
      "name": "PAUL R TREGURTHA",
      "type": 70,
      "lat": 44.94973,
      "lon": -86.10316,
      "sog": 13.2,
      "cog": 61,
      "heading": 60,
      "length": 309,
      "beam": 32,
      "destination": "DULUTH",
      "lastReport": "2026-07-08T18:01:36Z"
    },
    {
      "mmsi": 367120990,
      "name": "AMERICAN INTEGRITY",
      "type": 70,
      "lat": 46.69997,
      "lon": -92.01861,
      "sog": 0,
      "cog": 181,
      "heading": 181,
      "length": 305,
      "beam": 32,
      "destination": "ASHTABULA",
      "lastReport": "2026-07-08T18:01:13Z"
    },
    {
      "mmsi": 338866000,
      "name": "DIRK S. VANENKEVORT",
      "type": 52,
      "lat": 42.28843,
      "lon": -83.10265,
      "sog": 0,
      "cog": 31,
      "heading": 27,
      "length": 262,
      "beam": 24,
      "destination": "CALCITE",
      "lastReport": "2026-07-08T18:01:48Z"
    },
    {
      "mmsi": 366983440,
      "name": "JOYCE L VANENKEVORT",
      "type": 52,
      "lat": 41.87554,
      "lon": -82.20797,
      "sog": 12.5,
      "cog": 71,
      "heading": 71,
      "length": 257,
      "beam": 23,
      "destination": "BUFFALO",
      "lastReport": "2026-07-08T18:01:43Z"
    },
    {
      "mmsi": 366904890,
      "name": "HON JAMES L OBERSTAR",
      "type": 70,
      "lat": 47.43553,
      "lon": -88.6638,
      "sog": 12.8,
      "cog": 258,
      "heading": 258,
      "length": 246,
      "beam": 24,
      "destination": "DULUTH",
      "lastReport": "2026-07-08T18:01:33Z"
    },
    {
      "mmsi": 316029000,
      "name": "CSL NIAGARA",
      "type": 70,
      "lat": 43.05315,
      "lon": -82.41544,
      "sog": 10.7,
      "cog": 359,
      "heading": 0,
      "length": 225,
      "beam": 24,
      "destination": "SANDUSKY",
      "lastReport": "2026-07-08T18:01:28Z"
    },
    {
      "mmsi": 316001834,
      "name": "FRONTENAC",
      "type": 70,
      "lat": 48.4141,
      "lon": -89.22427,
      "sog": 0,
      "cog": 186,
      "heading": 269,
      "length": 223,
      "beam": 23,
      "destination": "MIDLAND",
      "lastReport": "2026-07-08T18:01:40Z"
    },
    {
      "mmsi": 366938780,
      "name": "JOHN J. BOLAND",
      "type": 70,
      "lat": 46.84546,
      "lon": -91.899,
      "sog": 12.7,
      "cog": 63,
      "heading": 63,
      "length": 207,
      "beam": 24,
      "destination": "DULUTH",
      "lastReport": "2026-07-08T18:01:10Z"
    },
    {
      "mmsi": 538006779,
      "name": "FEDERAL HUDSON",
      "type": 70,
      "lat": 43.00751,
      "lon": -79.21387,
      "sog": 8.1,
      "cog": 188,
      "heading": 190,
      "length": 200,
      "beam": 24,
      "destination": "USTOL",
      "lastReport": "2026-07-08T18:01:12Z"
    },
    {
      "mmsi": 316043882,
      "name": "ALGOMA INTREPID",
      "type": 70,
      "lat": 48.41474,
      "lon": -89.14506,
      "sog": 0,
      "cog": 189,
      "heading": 203,
      "length": 198,
      "beam": 24,
      "destination": "THUNDER BAY",
      "lastReport": "2026-07-08T18:01:47Z"
    },
    {
      "mmsi": 366938760,
      "name": "SAM LAUD",
      "type": 70,
      "lat": 41.95105,
      "lon": -87.39742,
      "sog": 12.3,
      "cog": 145,
      "heading": 144,
      "length": 193,
      "beam": 21,
      "destination": "WAUKEGAN",
      "lastReport": "2026-07-08T18:01:43Z"
    },
    {
      "mmsi": 316003880,
      "name": "EVERLAST",
      "type": 80,
      "lat": 43.26618,
      "lon": -79.78709,
      "sog": 0,
      "cog": 133,
      "heading": 133,
      "length": 164,
      "beam": 22,
      "destination": "SARNIA",
      "lastReport": "2026-07-08T18:00:47Z"
    },
    {
      "mmsi": 538011029,
      "name": "HURON",
      "type": 80,
      "lat": 42.9071,
      "lon": -82.45835,
      "sog": 0,
      "cog": 164,
      "heading": 12,
      "length": 157,
      "beam": 23,
      "destination": "CAMNT->CASNI",
      "lastReport": "2026-07-08T18:01:52Z"
    },
    {
      "mmsi": 244040000,
      "name": "HUMBERGRACHT",
      "type": 70,
      "lat": 42.82532,
      "lon": -82.48308,
      "sog": 9.4,
      "cog": 187,
      "heading": 185,
      "length": 138,
      "beam": 21,
      "destination": "BEGNE",
      "lastReport": "2026-07-08T18:00:51Z"
    },
    {
      "mmsi": 245911000,
      "name": "STELLA POLARIS",
      "type": 81,
      "lat": 43.26401,
      "lon": -79.78871,
      "sog": 0,
      "cog": 107,
      "heading": 197,
      "length": 117,
      "beam": 18,
      "destination": "BE ZEL > CA HAM",
      "lastReport": "2026-07-08T18:01:40Z"
    }
  ]
}