{
  "updated": "2026-07-03T14:16:32Z",
  "vessels": [
    {
      "mmsi": 338866000,
      "name": "DIRK S. VANENKEVORT",
      "type": 52,
      "lat": 42.58074,
      "lon": -82.55961,
      "sog": 8.7,
      "cog": 225,
      "heading": 225,
      "length": 262,
      "beam": 24,
      "destination": "XX XXX>US^0V8F",
      "lastReport": "2026-07-03T14:16:24Z"
    },
    {
      "mmsi": 316053597,
      "name": "ALGOMA BEAR",
      "type": 70,
      "lat": 42.86447,
      "lon": -82.47128,
      "sog": 10.3,
      "cog": 173,
      "heading": 174,
      "length": 226,
      "beam": 24,
      "destination": "HAMILTON",
      "lastReport": "2026-07-03T14:15:52Z"
    },
    {
      "mmsi": 316001633,
      "name": "CSL ASSINIBOINE",
      "type": 70,
      "lat": 43.34059,
      "lon": -79.62016,
      "sog": 11.6,
      "cog": 256,
      "heading": 255,
      "length": 226,
      "beam": 24,
      "destination": "HAMILTON",
      "lastReport": "2026-07-03T14:15:53Z"
    },
    {
      "mmsi": 316026694,
      "name": "CSL ST-LAURENT",
      "type": 70,
      "lat": 48.41416,
      "lon": -89.22231,
      "sog": 0,
      "cog": 125,
      "heading": 269,
      "length": 226,
      "beam": 24,
      "destination": "THUNDER BAY",
      "lastReport": "2026-07-03T14:15:22Z"
    },
    {
      "mmsi": 316029000,
      "name": "CSL NIAGARA",
      "type": 70,
      "lat": 43.90202,
      "lon": -76.76285,
      "sog": 11.5,
      "cog": 249,
      "heading": 249,
      "length": 225,
      "beam": 24,
      "destination": "SANDUSKY",
      "lastReport": "2026-07-03T14:15:40Z"
    },
    {
      "mmsi": 316023341,
      "name": "WHITEFISH BAY",
      "type": 70,
      "lat": 41.67481,
      "lon": -87.43755,
      "sog": 0,
      "cog": 245,
      "heading": 345,
      "length": 225,
      "beam": 25,
      "destination": "SEPT-ILES",
      "lastReport": "2026-07-03T14:15:39Z"
    },
    {
      "mmsi": 316001834,
      "name": "FRONTENAC",
      "type": 70,
      "lat": 43.13228,
      "lon": -79.19237,
      "sog": 0,
      "cog": 270,
      "heading": 2,
      "length": 223,
      "beam": 23,
      "destination": "HAMILTON",
      "lastReport": "2026-07-03T14:16:10Z"
    },
    {
      "mmsi": 366938710,
      "name": "AMERICAN MARINER",
      "type": 70,
      "lat": 42.52405,
      "lon": -82.66394,
      "sog": 8.6,
      "cog": 67,
      "heading": 67,
      "length": 222,
      "beam": 23,
      "destination": "CEDARVILLE",
      "lastReport": "2026-07-03T14:15:25Z"
    },
    {
      "mmsi": 316001701,
      "name": "JOHN D LEITCH",
      "type": 70,
      "lat": 43.19217,
      "lon": -79.20196,
      "sog": 0,
      "cog": 100,
      "heading": 157,
      "length": 222,
      "beam": 24,
      "destination": "CLARKSON",
      "lastReport": "2026-07-03T14:16:02Z"
    },
    {
      "mmsi": 366904930,
      "name": "HERBERT C JACKSON",
      "type": 70,
      "lat": 42.46064,
      "lon": -82.75739,
      "sog": 11.7,
      "cog": 48,
      "heading": 47,
      "length": 213,
      "beam": 23,
      "destination": "USRRJ>USTOL",
      "lastReport": "2026-07-03T14:15:27Z"
    },
    {
      "mmsi": 316036229,
      "name": "ALGOMA COMPASS",
      "type": 70,
      "lat": 42.75177,
      "lon": -79.48522,
      "sog": 11.4,
      "cog": 239,
      "heading": 238,
      "length": 207,
      "beam": 24,
      "destination": "GODERICH",
      "lastReport": "2026-07-03T14:15:36Z"
    },
    {
      "mmsi": 538007837,
      "name": "FEDERAL NAGARA",
      "type": 70,
      "lat": 48.42031,
      "lon": -89.17052,
      "sog": 0,
      "cog": 342,
      "heading": 273,
      "length": 200,
      "beam": 24,
      "destination": "CA THU",
      "lastReport": "2026-07-03T14:16:30Z"
    },
    {
      "mmsi": 538008902,
      "name": "FEDERAL RUHR",
      "type": 70,
      "lat": 43.11425,
      "lon": -79.19589,
      "sog": 0.3,
      "cog": 26,
      "heading": 14,
      "length": 200,
      "beam": 24,
      "destination": "CATHU> CAMTR",
      "lastReport": "2026-07-03T14:15:46Z"
    },
    {
      "mmsi": 316035905,
      "name": "ALGOMA INNOVATOR",
      "type": 70,
      "lat": 42.9664,
      "lon": -82.41265,
      "sog": 0.1,
      "cog": 84,
      "heading": 31,
      "length": 198,
      "beam": 24,
      "destination": "SOMBRA",
      "lastReport": "2026-07-03T14:15:55Z"
    },
    {
      "mmsi": 316002063,
      "name": "SEA EAGLE II",
      "type": 52,
      "lat": 41.89573,
      "lon": -83.02565,
      "sog": 10.5,
      "cog": 94,
      "heading": 94,
      "length": 164,
      "beam": 23,
      "destination": "DETROIT SMC ROUGE",
      "lastReport": "2026-07-03T14:15:21Z"
    },
    {
      "mmsi": 316055401,
      "name": "ALGOSOLIS",
      "type": 82,
      "lat": 43.1341,
      "lon": -79.19269,
      "sog": 1.6,
      "cog": 184,
      "heading": 182,
      "length": 144,
      "beam": 23,
      "destination": "NANTICOKE",
      "lastReport": "2026-07-03T14:15:35Z"
    },
    {
      "mmsi": 316051091,
      "name": "ALGOBERTA",
      "type": 80,
      "lat": 42.90835,
      "lon": -79.24364,
      "sog": 0,
      "cog": 197,
      "heading": 189,
      "length": 143,
      "beam": 23,
      "destination": "CANAN",
      "lastReport": "2026-07-03T14:16:17Z"
    },
    {
      "mmsi": 316017550,
      "name": "MCASPHALT ADVANTAGE",
      "type": 80,
      "lat": 42.96074,
      "lon": -82.41725,
      "sog": 0,
      "cog": 64,
      "heading": 36,
      "length": 140,
      "beam": 24,
      "destination": "SARNIA",
      "lastReport": "2026-07-03T14:15:50Z"
    }
  ]
}