{
  "updated": "2026-07-10T03:01:45Z",
  "vessels": [
    {
      "mmsi": 366971370,
      "name": "EDWIN H. GOTT",
      "type": 70,
      "lat": 46.75211,
      "lon": -92.13569,
      "sog": 0,
      "cog": 319,
      "heading": 137,
      "length": 305,
      "beam": 32,
      "destination": "SUPERIOR",
      "lastReport": "2026-07-10T03:01:35Z"
    },
    {
      "mmsi": 366930730,
      "name": "AMERICAN SPIRIT",
      "type": 70,
      "lat": 41.92145,
      "lon": -87.37552,
      "sog": 12.6,
      "cog": 351,
      "heading": 352,
      "length": 302,
      "beam": 32,
      "destination": "BUFFINGTON",
      "lastReport": "2026-07-10T03:01:16Z"
    },
    {
      "mmsi": 316026695,
      "name": "CSL WELLAND",
      "type": 70,
      "lat": 42.88313,
      "lon": -79.24874,
      "sog": 3.5,
      "cog": 180,
      "heading": 182,
      "length": 226,
      "beam": 24,
      "destination": "THUNDER BAY",
      "lastReport": "2026-07-10T03:01:11Z"
    },
    {
      "mmsi": 316001637,
      "name": "CSL LAURENTIEN",
      "type": 79,
      "lat": 43.64248,
      "lon": -79.36746,
      "sog": 0,
      "cog": 175,
      "heading": 243,
      "length": 225,
      "beam": 24,
      "destination": "TWO HARBORS",
      "lastReport": "2026-07-10T03:00:49Z"
    },
    {
      "mmsi": 316013966,
      "name": "OAKGLEN",
      "type": 70,
      "lat": 48.35557,
      "lon": -89.22908,
      "sog": 0,
      "cog": 250,
      "heading": 291,
      "length": 223,
      "beam": 23,
      "destination": "CATHU",
      "lastReport": "2026-07-10T03:01:23Z"
    },
    {
      "mmsi": 538007837,
      "name": "FEDERAL NAGARA",
      "type": 70,
      "lat": 43.15402,
      "lon": -79.19345,
      "sog": 0.8,
      "cog": 356,
      "heading": 355,
      "length": 200,
      "beam": 24,
      "destination": "CA MTR",
      "lastReport": "2026-07-10T03:01:36Z"
    },
    {
      "mmsi": 316017550,
      "name": "MCASPHALT ADVANTAGE",
      "type": 80,
      "lat": 42.95729,
      "lon": -82.42087,
      "sog": 0,
      "cog": 88,
      "heading": 41,
      "length": 140,
      "beam": 24,
      "destination": "SARNIA",
      "lastReport": "2026-07-10T03:01:30Z"
    },
    {
      "mmsi": 316002065,
      "name": "PETIT FORTE",
      "type": 31,
      "lat": 43.64274,
      "lon": -79.35404,
      "sog": 0,
      "cog": 63,
      "heading": 59,
      "length": 131,
      "beam": 18,
      "destination": "TORONTO",
      "lastReport": "2026-07-10T03:01:22Z"
    },
    {
      "mmsi": 316013215,
      "name": "ALGOCANADA",
      "type": 89,
      "lat": 42.61926,
      "lon": -79.76932,
      "sog": 11.6,
      "cog": 241,
      "heading": 239,
      "length": 130,
      "beam": 20,
      "destination": "SARNIA",
      "lastReport": "2026-07-10T03:00:38Z"
    },
    {
      "mmsi": 245911000,
      "name": "STELLA POLARIS",
      "type": 81,
      "lat": 43.50581,
      "lon": -78.54293,
      "sog": 13.3,
      "cog": 76,
      "heading": 76,
      "length": 117,
      "beam": 18,
      "destination": "BE ZEL > CA HAM",
      "lastReport": "2026-07-10T03:01:05Z"
    },
    {
      "mmsi": 244283000,
      "name": "IVER BRIGHT",
      "type": 89,
      "lat": 42.93402,
      "lon": -82.44711,
      "sog": 0,
      "cog": 208,
      "heading": 32,
      "length": 110,
      "beam": 18,
      "destination": "CASNI",
      "lastReport": "2026-07-10T03:01:21Z"
    }
  ]
}