{
  "updated": "2026-07-02T07:16:26Z",
  "vessels": [
    {
      "mmsi": 366971370,
      "name": "EDWIN H. GOTT",
      "type": 70,
      "lat": 47.01465,
      "lon": -91.67182,
      "sog": 0,
      "cog": 296,
      "heading": 297,
      "length": 305,
      "beam": 32,
      "destination": "TWO HARBORS",
      "lastReport": "2026-07-02T07:16:21Z"
    },
    {
      "mmsi": 316026694,
      "name": "CSL ST-LAURENT",
      "type": 70,
      "lat": 48.41416,
      "lon": -89.22052,
      "sog": 0,
      "cog": 192,
      "heading": 270,
      "length": 226,
      "beam": 24,
      "destination": "THUNDER BAY",
      "lastReport": "2026-07-02T07:15:21Z"
    },
    {
      "mmsi": 316023808,
      "name": "BAIE COMEAU",
      "type": 70,
      "lat": 43.24692,
      "lon": -79.21672,
      "sog": 7.7,
      "cog": 356,
      "heading": 352,
      "length": 225,
      "beam": 24,
      "destination": "HAMILTON",
      "lastReport": "2026-07-02T07:15:33Z"
    },
    {
      "mmsi": 366938710,
      "name": "AMERICAN MARINER",
      "type": 70,
      "lat": 42.49561,
      "lon": -82.71554,
      "sog": 11.2,
      "cog": 221,
      "heading": 221,
      "length": 222,
      "beam": 23,
      "destination": "LORAIN",
      "lastReport": "2026-07-02T07:15:24Z"
    },
    {
      "mmsi": 305594000,
      "name": "BBC KOLDING",
      "type": 70,
      "lat": 43.23683,
      "lon": -79.29163,
      "sog": 0,
      "cog": 342,
      "heading": 233,
      "length": 149,
      "beam": 23,
      "destination": "THUNDERBAY",
      "lastReport": "2026-07-02T07:15:49Z"
    }
  ]
}