{
  "updated": "2026-07-19T19:16:30Z",
  "vessels": [
    {
      "mmsi": 316001633,
      "name": "CSL ASSINIBOINE",
      "type": 70,
      "lat": 43.22144,
      "lon": -79.21513,
      "sog": 1,
      "cog": 161,
      "heading": 165,
      "length": 226,
      "beam": 24,
      "destination": "SUPERIOR WI",
      "lastReport": "2026-07-19T19:15:48Z"
    },
    {
      "mmsi": 316017110,
      "name": "ALGOMA ENDEAVOUR",
      "type": 70,
      "lat": 43.19324,
      "lon": -79.20257,
      "sog": 0.4,
      "cog": 339,
      "heading": 336,
      "length": 225,
      "beam": 24,
      "destination": "CLARKSON",
      "lastReport": "2026-07-19T19:15:56Z"
    },
    {
      "mmsi": 316001637,
      "name": "CSL LAURENTIEN",
      "type": 79,
      "lat": 42.48469,
      "lon": -79.89767,
      "sog": 11.3,
      "cog": 55,
      "heading": 55,
      "length": 225,
      "beam": 24,
      "destination": "TWO HARBORS",
      "lastReport": "2026-07-19T19:15:29Z"
    },
    {
      "mmsi": 316001701,
      "name": "JOHN D LEITCH",
      "type": 70,
      "lat": 46.91188,
      "lon": -91.53251,
      "sog": 10.7,
      "cog": 58,
      "heading": 57,
      "length": 222,
      "beam": 24,
      "destination": "SUPERIOR",
      "lastReport": "2026-07-19T19:15:57Z"
    },
    {
      "mmsi": 366938770,
      "name": "H LEE WHITE",
      "type": 70,
      "lat": 46.73702,
      "lon": -92.08964,
      "sog": 0,
      "cog": 134,
      "heading": 125,
      "length": 215,
      "beam": 24,
      "destination": "DULUTH",
      "lastReport": "2026-07-19T19:16:21Z"
    },
    {
      "mmsi": 366938780,
      "name": "JOHN J. BOLAND",
      "type": 70,
      "lat": 41.69605,
      "lon": -87.55275,
      "sog": 0,
      "cog": 342,
      "heading": 158,
      "length": 207,
      "beam": 24,
      "destination": "CHARLEVOIX",
      "lastReport": "2026-07-19T19:16:10Z"
    },
    {
      "mmsi": 538006753,
      "name": "FEDERAL ASAHI",
      "type": 70,
      "lat": 48.3539,
      "lon": -89.22895,
      "sog": 0,
      "cog": 76,
      "heading": 289,
      "length": 200,
      "beam": 24,
      "destination": "CATHU",
      "lastReport": "2026-07-19T19:16:06Z"
    },
    {
      "mmsi": 538006434,
      "name": "FEDERAL BISCAY",
      "type": 70,
      "lat": 42.8342,
      "lon": -79.27432,
      "sog": 2.7,
      "cog": 36,
      "heading": 35,
      "length": 200,
      "beam": 24,
      "destination": "MONTREAL",
      "lastReport": "2026-07-19T19:15:18Z"
    },
    {
      "mmsi": 316035905,
      "name": "ALGOMA INNOVATOR",
      "type": 70,
      "lat": 42.9019,
      "lon": -82.46675,
      "sog": 10.1,
      "cog": 199,
      "heading": 197,
      "length": 198,
      "beam": 24,
      "destination": "HAMILTON",
      "lastReport": "2026-07-19T19:16:00Z"
    },
    {
      "mmsi": 316043882,
      "name": "ALGOMA INTREPID",
      "type": 70,
      "lat": 42.82313,
      "lon": -78.85804,
      "sog": 0,
      "cog": 233,
      "heading": 162,
      "length": 198,
      "beam": 24,
      "destination": "BUFFALO",
      "lastReport": "2026-07-19T19:15:59Z"
    },
    {
      "mmsi": 209016000,
      "name": "TORRENT",
      "type": 70,
      "lat": 43.04199,
      "lon": -79.21273,
      "sog": 5.2,
      "cog": 359,
      "heading": 358,
      "length": 185,
      "beam": 24,
      "destination": "CA MTR",
      "lastReport": "2026-07-19T19:15:23Z"
    },
    {
      "mmsi": 316013946,
      "name": "LEO A.MCARTHUR",
      "type": 80,
      "lat": 43.26834,
      "lon": -79.78623,
      "sog": 0,
      "cog": 188,
      "heading": 198,
      "length": 152,
      "beam": 22,
      "destination": "HAMILTON",
      "lastReport": "2026-07-19T19:16:01Z"
    },
    {
      "mmsi": 316055401,
      "name": "ALGOSOLIS",
      "type": 89,
      "lat": 43.13229,
      "lon": -79.19237,
      "sog": 0.6,
      "cog": 1,
      "heading": 2,
      "length": 144,
      "beam": 23,
      "destination": "NANTICOKE",
      "lastReport": "2026-07-19T19:16:14Z"
    }
  ]
}