{
  "updated": "2026-07-12T16:31:41Z",
  "vessels": [
    {
      "mmsi": 366938730,
      "name": "INDIANA HARBOR",
      "type": 70,
      "lat": 42.21963,
      "lon": -83.13133,
      "sog": 8.7,
      "cog": 5,
      "heading": 4,
      "length": 305,
      "beam": 32,
      "destination": "TWO HARBORS,MN",
      "lastReport": "2026-07-12T16:30:59Z"
    },
    {
      "mmsi": 338866000,
      "name": "DIRK S. VANENKEVORT",
      "type": 52,
      "lat": 46.69934,
      "lon": -92.01856,
      "sog": 0,
      "cog": 184,
      "heading": 182,
      "length": 262,
      "beam": 24,
      "destination": "SUPERIOR",
      "lastReport": "2026-07-12T16:31:34Z"
    },
    {
      "mmsi": 316001633,
      "name": "CSL ASSINIBOINE",
      "type": 70,
      "lat": 43.15367,
      "lon": -79.19339,
      "sog": 0.7,
      "cog": 352,
      "heading": 354,
      "length": 226,
      "beam": 24,
      "destination": "QUEBEC CITY",
      "lastReport": "2026-07-12T16:30:30Z"
    },
    {
      "mmsi": 316026695,
      "name": "CSL WELLAND",
      "type": 70,
      "lat": 48.11059,
      "lon": -88.10132,
      "sog": 12.3,
      "cog": 301,
      "heading": 300,
      "length": 226,
      "beam": 24,
      "destination": "THUNDER BAY",
      "lastReport": "2026-07-12T16:30:38Z"
    },
    {
      "mmsi": 316001635,
      "name": "RT HON PAUL J MARTIN",
      "type": 70,
      "lat": 43.54806,
      "lon": -78.02571,
      "sog": 11.7,
      "cog": 73,
      "heading": 73,
      "length": 225,
      "beam": 24,
      "destination": "BECANCOUR",
      "lastReport": "2026-07-12T16:30:41Z"
    },
    {
      "mmsi": 367480250,
      "name": "OLIVE L. MOORE",
      "type": 52,
      "lat": 42.41486,
      "lon": -82.82602,
      "sog": 6.9,
      "cog": 228,
      "heading": 229,
      "length": 222,
      "beam": 22,
      "destination": "RIVER ROUGE 67",
      "lastReport": "2026-07-12T16:30:50Z"
    },
    {
      "mmsi": 316035905,
      "name": "ALGOMA INNOVATOR",
      "type": 70,
      "lat": 43.19988,
      "lon": -79.20684,
      "sog": 0,
      "cog": 90,
      "heading": 156,
      "length": 198,
      "beam": 24,
      "destination": "PORT  COLBORNE",
      "lastReport": "2026-07-12T16:31:14Z"
    },
    {
      "mmsi": 316036228,
      "name": "ALGOMA BUFFALO",
      "type": 70,
      "lat": 42.89822,
      "lon": -79.24615,
      "sog": 0,
      "cog": 30,
      "heading": 10,
      "length": 194,
      "beam": 21,
      "destination": "CLEVELAND",
      "lastReport": "2026-07-12T16:31:05Z"
    },
    {
      "mmsi": 366938760,
      "name": "SAM LAUD",
      "type": 70,
      "lat": 42.76088,
      "lon": -82.46752,
      "sog": 10,
      "cog": 11,
      "heading": 7,
      "length": 193,
      "beam": 21,
      "destination": "CALCITE",
      "lastReport": "2026-07-12T16:31:22Z"
    },
    {
      "mmsi": 229656000,
      "name": "VERILA",
      "type": 79,
      "lat": 43.74125,
      "lon": -77.43503,
      "sog": 13.8,
      "cog": 255,
      "heading": 256,
      "length": 190,
      "beam": 24,
      "destination": "CA HAM",
      "lastReport": "2026-07-12T16:30:37Z"
    },
    {
      "mmsi": 316036419,
      "name": "MCKEIL SPIRIT",
      "type": 70,
      "lat": 44.12335,
      "lon": -76.8558,
      "sog": 12.7,
      "cog": 235,
      "heading": 233,
      "length": 140,
      "beam": 21,
      "destination": "USROC",
      "lastReport": "2026-07-12T16:31:34Z"
    },
    {
      "mmsi": 245278000,
      "name": "EEMSBORG",
      "type": 79,
      "lat": 42.73617,
      "lon": -79.46367,
      "sog": 11.1,
      "cog": 242,
      "heading": 242,
      "length": 138,
      "beam": 16,
      "destination": "USDTT",
      "lastReport": "2026-07-12T16:31:20Z"
    },
    {
      "mmsi": 316002065,
      "name": "PETIT FORTE",
      "type": 31,
      "lat": 43.2282,
      "lon": -79.21783,
      "sog": 0,
      "cog": 149,
      "heading": 164,
      "length": 131,
      "beam": 18,
      "destination": "OWEN SOUND",
      "lastReport": "2026-07-12T16:31:21Z"
    },
    {
      "mmsi": 316041965,
      "name": "TAMARACK",
      "type": 70,
      "lat": 42.43798,
      "lon": -79.85263,
      "sog": 10.8,
      "cog": 228,
      "heading": 227,
      "length": 123,
      "beam": 23,
      "destination": "CLEVELAND",
      "lastReport": "2026-07-12T16:31:24Z"
    }
  ]
}