{
  "updated": "2026-07-23T10:31:47Z",
  "vessels": [
    {
      "mmsi": 366938730,
      "name": "INDIANA HARBOR",
      "type": 70,
      "lat": 46.75193,
      "lon": -92.13568,
      "sog": 0,
      "cog": 332,
      "heading": 136,
      "length": 305,
      "beam": 32,
      "destination": "DULUTH, MN",
      "lastReport": "2026-07-23T10:31:19Z"
    },
    {
      "mmsi": 366905890,
      "name": "JAMES R BARKER",
      "type": 70,
      "lat": 41.93297,
      "lon": -87.45811,
      "sog": 10.7,
      "cog": 180,
      "heading": 180,
      "length": 305,
      "beam": 32,
      "destination": "INDIANA HARBOR",
      "lastReport": "2026-07-23T10:31:19Z"
    },
    {
      "mmsi": 366906610,
      "name": "WALTER J MCCARTHY",
      "type": 70,
      "lat": 41.9126,
      "lon": -87.37588,
      "sog": 12,
      "cog": 350,
      "heading": 349,
      "length": 305,
      "beam": 32,
      "destination": "GARY CH 74",
      "lastReport": "2026-07-23T10:30:51Z"
    },
    {
      "mmsi": 316026695,
      "name": "CSL WELLAND",
      "type": 70,
      "lat": 43.13224,
      "lon": -79.19295,
      "sog": 0,
      "cog": 11,
      "heading": 183,
      "length": 226,
      "beam": 24,
      "destination": "MONTREAL",
      "lastReport": "2026-07-23T10:31:03Z"
    },
    {
      "mmsi": 316023808,
      "name": "BAIE COMEAU",
      "type": 70,
      "lat": 43.28193,
      "lon": -79.82775,
      "sog": 0,
      "cog": 306,
      "heading": 18,
      "length": 225,
      "beam": 24,
      "destination": "HAMILTON",
      "lastReport": "2026-07-23T10:31:03Z"
    },
    {
      "mmsi": 316001635,
      "name": "RT HON PAUL J MARTIN",
      "type": 70,
      "lat": 48.41427,
      "lon": -89.21548,
      "sog": 0.6,
      "cog": 252,
      "heading": 263,
      "length": 225,
      "beam": 24,
      "destination": "BECANCOUR",
      "lastReport": "2026-07-23T10:31:32Z"
    },
    {
      "mmsi": 316023341,
      "name": "WHITEFISH BAY",
      "type": 70,
      "lat": 43.60257,
      "lon": -79.03194,
      "sog": 12,
      "cog": 84,
      "heading": 83,
      "length": 225,
      "beam": 25,
      "destination": "PICTON",
      "lastReport": "2026-07-23T10:31:19Z"
    },
    {
      "mmsi": 316001834,
      "name": "FRONTENAC",
      "type": 70,
      "lat": 43.18745,
      "lon": -79.19859,
      "sog": 2,
      "cog": 160,
      "heading": 156,
      "length": 223,
      "beam": 23,
      "destination": "THUNDER BAY CH67",
      "lastReport": "2026-07-23T10:31:27Z"
    },
    {
      "mmsi": 316018031,
      "name": "ALGOMA GUARDIAN",
      "type": 70,
      "lat": 42.76567,
      "lon": -79.37167,
      "sog": 12.9,
      "cog": 53,
      "heading": 54,
      "length": 222,
      "beam": 23,
      "destination": "HAMILTON",
      "lastReport": "2026-07-23T10:31:19Z"
    },
    {
      "mmsi": 316001701,
      "name": "JOHN D LEITCH",
      "type": 70,
      "lat": 43.12724,
      "lon": -79.19286,
      "sog": 0.9,
      "cog": 9,
      "heading": 10,
      "length": 222,
      "beam": 24,
      "destination": "HAMILTON",
      "lastReport": "2026-07-23T10:31:36Z"
    },
    {
      "mmsi": 367480250,
      "name": "OLIVE L. MOORE",
      "type": 52,
      "lat": 42.96118,
      "lon": -82.42136,
      "sog": 8.6,
      "cog": 210,
      "heading": 211,
      "length": 222,
      "beam": 22,
      "destination": "MONROE",
      "lastReport": "2026-07-23T10:31:22Z"
    },
    {
      "mmsi": 366904930,
      "name": "HERBERT C JACKSON",
      "type": 70,
      "lat": 42.16468,
      "lon": -80.3328,
      "sog": 12,
      "cog": 246,
      "heading": 245,
      "length": 213,
      "beam": 23,
      "destination": "USMKE>USGUV",
      "lastReport": "2026-07-23T10:31:19Z"
    },
    {
      "mmsi": 316059017,
      "name": "ONTARIO VENTURE",
      "type": 70,
      "lat": 42.28122,
      "lon": -83.13022,
      "sog": 0,
      "cog": 15,
      "heading": 292,
      "length": 207,
      "beam": 24,
      "destination": "DETROIT",
      "lastReport": "2026-07-23T10:31:19Z"
    },
    {
      "mmsi": 367082220,
      "name": "WILFRED SYKES",
      "type": 70,
      "lat": 41.67504,
      "lon": -87.43774,
      "sog": 0,
      "cog": 166,
      "heading": 345,
      "length": 201,
      "beam": 21,
      "destination": "INDIANA HBR,. IN",
      "lastReport": "2026-07-23T10:31:41Z"
    },
    {
      "mmsi": 538006753,
      "name": "FEDERAL ASAHI",
      "type": 70,
      "lat": 43.18713,
      "lon": -79.19919,
      "sog": 2.9,
      "cog": 336,
      "heading": 336,
      "length": 200,
      "beam": 24,
      "destination": "CAMTR",
      "lastReport": "2026-07-23T10:31:26Z"
    },
    {
      "mmsi": 367121040,
      "name": "AMERICAN COURAGE",
      "type": 70,
      "lat": 41.49723,
      "lon": -81.72212,
      "sog": 0,
      "cog": 48,
      "heading": 56,
      "length": 194,
      "beam": 21,
      "destination": "CLEVELAND",
      "lastReport": "2026-07-23T10:31:03Z"
    },
    {
      "mmsi": 316011905,
      "name": "ROBERT S. PIERSON",
      "type": 70,
      "lat": 42.3403,
      "lon": -82.92236,
      "sog": 0,
      "cog": 299,
      "heading": 89,
      "length": 192,
      "beam": 21,
      "destination": "WINDSOR CH 69",
      "lastReport": "2026-07-23T10:31:19Z"
    },
    {
      "mmsi": 212372000,
      "name": "BRANT",
      "type": 70,
      "lat": 43.64235,
      "lon": -79.36813,
      "sog": 0,
      "cog": 333,
      "heading": 334,
      "length": 185,
      "beam": 24,
      "destination": "TORONTO",
      "lastReport": "2026-07-23T10:31:19Z"
    },
    {
      "mmsi": 366937490,
      "name": "GL OSTRANDER",
      "type": 52,
      "lat": 42.36412,
      "lon": -87.82373,
      "sog": 0,
      "cog": 318,
      "heading": 309,
      "length": 178,
      "beam": 21,
      "destination": "WAUKEGAN",
      "lastReport": "2026-07-23T10:31:27Z"
    },
    {
      "mmsi": 316003880,
      "name": "EVERLAST",
      "type": 80,
      "lat": 43.26618,
      "lon": -79.78708,
      "sog": 0,
      "cog": 223,
      "heading": 223,
      "length": 164,
      "beam": 22,
      "destination": "SARNIA",
      "lastReport": "2026-07-23T10:31:19Z"
    },
    {
      "mmsi": 316002063,
      "name": "SEA EAGLE II",
      "type": 52,
      "lat": 43.87291,
      "lon": -78.68329,
      "sog": 0,
      "cog": 62,
      "heading": 243,
      "length": 164,
      "beam": 23,
      "destination": "BOWMANVILLE",
      "lastReport": "2026-07-23T10:31:19Z"
    },
    {
      "mmsi": 316052496,
      "name": "NORTHERN VENTURE",
      "type": 70,
      "lat": 43.2163,
      "lon": -79.20756,
      "sog": 0,
      "cog": 331,
      "heading": 239,
      "length": 155,
      "beam": 22,
      "destination": "HAMILTON P22",
      "lastReport": "2026-07-23T10:31:27Z"
    },
    {
      "mmsi": 366893910,
      "name": "ALPENA",
      "type": 70,
      "lat": 42.43303,
      "lon": -82.79888,
      "sog": 11.3,
      "cog": 48,
      "heading": 47,
      "length": 153,
      "beam": 20,
      "destination": "ALPENA",
      "lastReport": "2026-07-23T10:31:22Z"
    },
    {
      "mmsi": 316013946,
      "name": "LEO A.MCARTHUR",
      "type": 80,
      "lat": 43.26834,
      "lon": -79.78622,
      "sog": 0,
      "cog": 255,
      "heading": 198,
      "length": 152,
      "beam": 22,
      "destination": "HAMILTON",
      "lastReport": "2026-07-23T10:31:24Z"
    },
    {
      "mmsi": 255915987,
      "name": "STENHEIM",
      "type": 80,
      "lat": 42.65261,
      "lon": -79.69802,
      "sog": 12,
      "cog": 240,
      "heading": 240,
      "length": 144,
      "beam": 23,
      "destination": "US DET",
      "lastReport": "2026-07-23T10:31:19Z"
    },
    {
      "mmsi": 246771000,
      "name": "MUNTGRACHT",
      "type": 70,
      "lat": 42.78601,
      "lon": -79.39773,
      "sog": 14.3,
      "cog": 240,
      "heading": 240,
      "length": 142,
      "beam": 19,
      "destination": "US TOL",
      "lastReport": "2026-07-23T10:31:24Z"
    },
    {
      "mmsi": 316040257,
      "name": "HINCH SPIRIT",
      "type": 89,
      "lat": 43.29546,
      "lon": -79.8365,
      "sog": 0,
      "cog": 311,
      "heading": 264,
      "length": 137,
      "beam": 20,
      "destination": "CAHAM",
      "lastReport": "2026-07-23T10:31:36Z"
    },
    {
      "mmsi": 316002065,
      "name": "PETIT FORTE",
      "type": 31,
      "lat": 43.1541,
      "lon": -79.19344,
      "sog": 1.7,
      "cog": 176,
      "heading": 174,
      "length": 131,
      "beam": 18,
      "destination": "BOWMANVILLE",
      "lastReport": "2026-07-23T10:31:19Z"
    },
    {
      "mmsi": 316041965,
      "name": "TAMARACK",
      "type": 70,
      "lat": 44.16375,
      "lon": -76.80111,
      "sog": 0,
      "cog": 8,
      "heading": 237,
      "length": 123,
      "beam": 23,
      "destination": "BUFFALO",
      "lastReport": "2026-07-23T10:31:19Z"
    }
  ]
}