{
  "updated": "2026-07-09T00:31:50Z",
  "vessels": [
    {
      "mmsi": 366971370,
      "name": "EDWIN H. GOTT",
      "type": 70,
      "lat": 47.15816,
      "lon": -90.70602,
      "sog": 14.1,
      "cog": 257,
      "heading": 257,
      "length": 305,
      "beam": 32,
      "destination": "SUPERIOR",
      "lastReport": "2026-07-09T00:31:07Z"
    },
    {
      "mmsi": 338866000,
      "name": "DIRK S. VANENKEVORT",
      "type": 52,
      "lat": 42.29033,
      "lon": -83.09905,
      "sog": 3.7,
      "cog": 52,
      "heading": 45,
      "length": 262,
      "beam": 24,
      "destination": "XX XXX>?? ???",
      "lastReport": "2026-07-09T00:31:08Z"
    },
    {
      "mmsi": 366904890,
      "name": "HON JAMES L OBERSTAR",
      "type": 70,
      "lat": 47.13755,
      "lon": -90.64833,
      "sog": 12.9,
      "cog": 258,
      "heading": 258,
      "length": 246,
      "beam": 24,
      "destination": "DULUTH",
      "lastReport": "2026-07-09T00:31:23Z"
    },
    {
      "mmsi": 316001844,
      "name": "SPRUCEGLEN",
      "type": 70,
      "lat": 44.14497,
      "lon": -76.33332,
      "sog": 11.7,
      "cog": 214,
      "heading": 213,
      "length": 223,
      "beam": 24,
      "destination": "THUNDER BAY",
      "lastReport": "2026-07-09T00:30:41Z"
    },
    {
      "mmsi": 366938780,
      "name": "JOHN J. BOLAND",
      "type": 70,
      "lat": 47.33215,
      "lon": -90.02371,
      "sog": 12.6,
      "cog": 80,
      "heading": 79,
      "length": 207,
      "beam": 24,
      "destination": "MARQUETTE",
      "lastReport": "2026-07-09T00:30:49Z"
    },
    {
      "mmsi": 538006469,
      "name": "FEDERAL CHURCHILL",
      "type": 70,
      "lat": 47.93019,
      "lon": -89.48542,
      "sog": 14.7,
      "cog": 56,
      "heading": 55,
      "length": 200,
      "beam": 23,
      "destination": "CA THU",
      "lastReport": "2026-07-09T00:30:55Z"
    },
    {
      "mmsi": 538006779,
      "name": "FEDERAL HUDSON",
      "type": 70,
      "lat": 42.37404,
      "lon": -80.42946,
      "sog": 13.5,
      "cog": 247,
      "heading": 248,
      "length": 200,
      "beam": 24,
      "destination": "USTOL",
      "lastReport": "2026-07-09T00:30:43Z"
    },
    {
      "mmsi": 538007837,
      "name": "FEDERAL NAGARA",
      "type": 70,
      "lat": 42.4169,
      "lon": -82.82367,
      "sog": 11.4,
      "cog": 228,
      "heading": 229,
      "length": 200,
      "beam": 24,
      "destination": "CA MTR",
      "lastReport": "2026-07-09T00:30:43Z"
    },
    {
      "mmsi": 255916529,
      "name": "POLSTEAM WIGRY",
      "type": 70,
      "lat": 48.40863,
      "lon": -89.18708,
      "sog": 0,
      "cog": 58,
      "heading": 170,
      "length": 200,
      "beam": 24,
      "destination": "CA THU",
      "lastReport": "2026-07-09T00:31:44Z"
    },
    {
      "mmsi": 316011905,
      "name": "ROBERT S. PIERSON",
      "type": 70,
      "lat": 42.36173,
      "lon": -82.90831,
      "sog": 9.5,
      "cog": 68,
      "heading": 65,
      "length": 192,
      "beam": 21,
      "destination": "WINDSOR CH 69",
      "lastReport": "2026-07-09T00:31:18Z"
    },
    {
      "mmsi": 538004060,
      "name": "FEDERAL KUSHIRO",
      "type": 70,
      "lat": 43.28802,
      "lon": -79.82442,
      "sog": 6.8,
      "cog": 90,
      "heading": 90,
      "length": 190,
      "beam": 24,
      "destination": "CA HAM",
      "lastReport": "2026-07-09T00:30:48Z"
    },
    {
      "mmsi": 209016000,
      "name": "TORRENT",
      "type": 70,
      "lat": 48.4129,
      "lon": -89.16784,
      "sog": 0.3,
      "cog": 331,
      "heading": 220,
      "length": 185,
      "beam": 24,
      "destination": "CA THU",
      "lastReport": "2026-07-09T00:31:18Z"
    },
    {
      "mmsi": 367159020,
      "name": "ALBERT",
      "type": 52,
      "lat": 42.22628,
      "lon": -83.13054,
      "sog": 6.2,
      "cog": 6,
      "heading": 2,
      "length": 152,
      "beam": 23,
      "destination": "TOLEDO",
      "lastReport": "2026-07-09T00:30:51Z"
    },
    {
      "mmsi": 636024470,
      "name": "GOLDEN PALM",
      "type": 80,
      "lat": 42.95921,
      "lon": -82.4187,
      "sog": 0,
      "cog": 200,
      "heading": 36,
      "length": 150,
      "beam": 23,
      "destination": "USBTR",
      "lastReport": "2026-07-09T00:31:03Z"
    },
    {
      "mmsi": 305594000,
      "name": "BBC KOLDING",
      "type": 70,
      "lat": 48.41729,
      "lon": -89.21915,
      "sog": 0,
      "cog": 317,
      "heading": 268,
      "length": 149,
      "beam": 23,
      "destination": "THUNDERBAY",
      "lastReport": "2026-07-09T00:31:32Z"
    }
  ]
}