{
  "updated": "2026-07-01T21:16:28Z",
  "vessels": [
    {
      "mmsi": 366971370,
      "name": "EDWIN H. GOTT",
      "type": 70,
      "lat": 47.00249,
      "lon": -91.64863,
      "sog": 8.5,
      "cog": 256,
      "heading": 257,
      "length": 305,
      "beam": 32,
      "destination": "TWO HARBORS",
      "lastReport": "2026-07-01T21:15:40Z"
    },
    {
      "mmsi": 316011710,
      "name": "ALGOMA HARVESTER",
      "type": 70,
      "lat": 48.22434,
      "lon": -88.41243,
      "sog": 12.9,
      "cog": 119,
      "heading": 123,
      "length": 225,
      "beam": 24,
      "destination": "THUNDER BAY",
      "lastReport": "2026-07-01T21:16:10Z"
    },
    {
      "mmsi": 316023808,
      "name": "BAIE COMEAU",
      "type": 70,
      "lat": 43.11647,
      "lon": -79.19504,
      "sog": 0,
      "cog": 334,
      "heading": 8,
      "length": 225,
      "beam": 24,
      "destination": "HAMILTON",
      "lastReport": "2026-07-01T21:15:52Z"
    },
    {
      "mmsi": 366938770,
      "name": "H LEE WHITE",
      "type": 70,
      "lat": 42.88721,
      "lon": -82.47225,
      "sog": 9.9,
      "cog": 181,
      "heading": 180,
      "length": 215,
      "beam": 24,
      "destination": "CLEVELAND",
      "lastReport": "2026-07-01T21:15:39Z"
    },
    {
      "mmsi": 316002063,
      "name": "SEA EAGLE II",
      "type": 52,
      "lat": 42.28466,
      "lon": -83.13795,
      "sog": 0,
      "cog": 42,
      "heading": 149,
      "length": 164,
      "beam": 23,
      "destination": "DETROIT SMC ROUGE",
      "lastReport": "2026-07-01T21:15:52Z"
    },
    {
      "mmsi": 266463000,
      "name": "THUN VENERN",
      "type": 80,
      "lat": 43.12329,
      "lon": -79.1939,
      "sog": 0,
      "cog": 194,
      "heading": 190,
      "length": 150,
      "beam": 23,
      "destination": "CA SNI",
      "lastReport": "2026-07-01T21:15:52Z"
    },
    {
      "mmsi": 244283000,
      "name": "IVER BRIGHT",
      "type": 89,
      "lat": 42.93403,
      "lon": -82.44709,
      "sog": 0,
      "cog": 20,
      "heading": 31,
      "length": 110,
      "beam": 18,
      "destination": "CASNI",
      "lastReport": "2026-07-01T21:15:32Z"
    }
  ]
}