{
  "updated": "2026-07-17T07:46:31Z",
  "vessels": [
    {
      "mmsi": 338866000,
      "name": "DIRK S. VANENKEVORT",
      "type": 52,
      "lat": 42.92189,
      "lon": -82.45713,
      "sog": 7.1,
      "cog": 14,
      "heading": 14,
      "length": 262,
      "beam": 24,
      "destination": "CALCITE",
      "lastReport": "2026-07-17T07:46:05Z"
    },
    {
      "mmsi": 366983440,
      "name": "JOYCE L VANENKEVORT",
      "type": 52,
      "lat": 41.9068,
      "lon": -80.7937,
      "sog": 0,
      "cog": 356,
      "heading": 2,
      "length": 257,
      "beam": 23,
      "destination": "ASHTABULA OH",
      "lastReport": "2026-07-17T07:46:04Z"
    },
    {
      "mmsi": 316026695,
      "name": "CSL WELLAND",
      "type": 70,
      "lat": 42.26372,
      "lon": -80.70163,
      "sog": 12.2,
      "cog": 72,
      "heading": 71,
      "length": 226,
      "beam": 24,
      "destination": "MONTREAL",
      "lastReport": "2026-07-17T07:45:29Z"
    },
    {
      "mmsi": 316036089,
      "name": "ALGOMA SAULT",
      "type": 70,
      "lat": 43.43571,
      "lon": -79.04083,
      "sog": 13.6,
      "cog": 246,
      "heading": 245,
      "length": 225,
      "beam": 24,
      "destination": "JOHNSTOWN",
      "lastReport": "2026-07-17T07:45:21Z"
    },
    {
      "mmsi": 316001844,
      "name": "SPRUCEGLEN",
      "type": 70,
      "lat": 42.48027,
      "lon": -79.89424,
      "sog": 12.4,
      "cog": 54,
      "heading": 53,
      "length": 223,
      "beam": 24,
      "destination": "SOREL",
      "lastReport": "2026-07-17T07:45:27Z"
    },
    {
      "mmsi": 316018031,
      "name": "ALGOMA GUARDIAN",
      "type": 70,
      "lat": 42.12994,
      "lon": -81.35792,
      "sog": 13.7,
      "cog": 249,
      "heading": 250,
      "length": 222,
      "beam": 23,
      "destination": "HAMILTON",
      "lastReport": "2026-07-17T07:46:18Z"
    },
    {
      "mmsi": 316035905,
      "name": "ALGOMA INNOVATOR",
      "type": 70,
      "lat": 46.69894,
      "lon": -92.01861,
      "sog": 0,
      "cog": 323,
      "heading": 180,
      "length": 198,
      "beam": 24,
      "destination": "SUPERIOR",
      "lastReport": "2026-07-17T07:46:14Z"
    },
    {
      "mmsi": 366578000,
      "name": "UNDAUNTED",
      "type": 31,
      "lat": 42.97936,
      "lon": -87.41927,
      "sog": 9.2,
      "cog": 182,
      "heading": 179,
      "length": 150,
      "beam": 18,
      "destination": "S CHICAGO",
      "lastReport": "2026-07-17T07:45:44Z"
    },
    {
      "mmsi": 316015050,
      "name": "ALGOTERRA",
      "type": 82,
      "lat": 42.798,
      "lon": -80.04345,
      "sog": 0,
      "cog": 343,
      "heading": 163,
      "length": 144,
      "beam": 23,
      "destination": "CA NNR",
      "lastReport": "2026-07-17T07:46:11Z"
    },
    {
      "mmsi": 229594000,
      "name": "YM AMAZON",
      "type": 70,
      "lat": 42.22048,
      "lon": -83.13116,
      "sog": 10.4,
      "cog": 185,
      "heading": 184,
      "length": 131,
      "beam": 19,
      "destination": "ESSDR",
      "lastReport": "2026-07-17T07:45:43Z"
    },
    {
      "mmsi": 316041965,
      "name": "TAMARACK",
      "type": 70,
      "lat": 43.64296,
      "lon": -79.35359,
      "sog": 0,
      "cog": 61,
      "heading": 59,
      "length": 123,
      "beam": 23,
      "destination": "TORONTO,ON",
      "lastReport": "2026-07-17T07:45:49Z"
    }
  ]
}