{
  "updated": "2026-07-05T07:46:27Z",
  "vessels": [
    {
      "mmsi": 366904890,
      "name": "HON JAMES L OBERSTAR",
      "type": 70,
      "lat": 41.67545,
      "lon": -87.43781,
      "sog": 0,
      "cog": 124,
      "heading": 344,
      "length": 246,
      "beam": 24,
      "destination": "INDIANA HARBOR",
      "lastReport": "2026-07-05T07:45:33Z"
    },
    {
      "mmsi": 316001836,
      "name": "CSL TADOUSSAC",
      "type": 70,
      "lat": 43.55834,
      "lon": -79.30301,
      "sog": 11.4,
      "cog": 248,
      "heading": 249,
      "length": 223,
      "beam": 23,
      "destination": "COLBORNE",
      "lastReport": "2026-07-05T07:45:40Z"
    },
    {
      "mmsi": 538006434,
      "name": "FEDERAL BISCAY",
      "type": 70,
      "lat": 43.1321,
      "lon": -79.19283,
      "sog": 0,
      "cog": 141,
      "heading": 184,
      "length": 200,
      "beam": 24,
      "destination": "CHICAGO, USA",
      "lastReport": "2026-07-05T07:45:32Z"
    },
    {
      "mmsi": 538006469,
      "name": "FEDERAL CHURCHILL",
      "type": 70,
      "lat": 46.75215,
      "lon": -92.0965,
      "sog": 0,
      "cog": 125,
      "heading": 242,
      "length": 200,
      "beam": 23,
      "destination": "US DLH",
      "lastReport": "2026-07-05T07:45:52Z"
    },
    {
      "mmsi": 316036228,
      "name": "ALGOMA BUFFALO",
      "type": 70,
      "lat": 43.3574,
      "lon": -79.24404,
      "sog": 2.9,
      "cog": 165,
      "heading": 160,
      "length": 194,
      "beam": 21,
      "destination": "GODERICH",
      "lastReport": "2026-07-05T07:45:43Z"
    },
    {
      "mmsi": 367340990,
      "name": "CALUMET",
      "type": 70,
      "lat": 42.92102,
      "lon": -82.46044,
      "sog": 0,
      "cog": 15,
      "heading": 10,
      "length": 191,
      "beam": 20,
      "destination": "MARYSVILLE",
      "lastReport": "2026-07-05T07:45:45Z"
    },
    {
      "mmsi": 538004060,
      "name": "FEDERAL KUSHIRO",
      "type": 70,
      "lat": 43.27268,
      "lon": -79.8409,
      "sog": 0,
      "cog": 232,
      "heading": 198,
      "length": 190,
      "beam": 24,
      "destination": "CA HAM",
      "lastReport": "2026-07-05T07:45:15Z"
    },
    {
      "mmsi": 636024470,
      "name": "GOLDEN PALM",
      "type": 80,
      "lat": 42.95923,
      "lon": -82.41869,
      "sog": 0,
      "cog": 118,
      "heading": 36,
      "length": 150,
      "beam": 23,
      "destination": "CASNI",
      "lastReport": "2026-07-05T07:46:03Z"
    },
    {
      "mmsi": 244283000,
      "name": "IVER BRIGHT",
      "type": 89,
      "lat": 42.934,
      "lon": -82.4471,
      "sog": 0,
      "cog": 129,
      "heading": 32,
      "length": 110,
      "beam": 18,
      "destination": "CASNI",
      "lastReport": "2026-07-05T07:45:19Z"
    }
  ]
}