{
  "367648960": {
    "name": "LUCIA",
    "type": 60,
    "length": 26,
    "beam": 9,
    "destination": "CHICAGO",
    "callsign": "WDH7517"
  },
  "316048072": {
    "name": "THOUSAND ISLANDER 3",
    "type": 60,
    "length": 36,
    "beam": 10,
    "destination": "",
    "callsign": ""
  },
  "367347610": {
    "name": "SHORELINE II",
    "type": 99,
    "length": 22,
    "beam": 8,
    "destination": "",
    "callsign": "WCY4503"
  },
  "338924003": {
    "name": "R/V LAKE EXPLORER II",
    "type": 33,
    "length": 27,
    "beam": 6,
    "destination": "SUPERIOR, WI",
    "callsign": "WDD6962"
  },
  "316023274": {
    "name": "MU22",
    "type": 55,
    "length": 10,
    "beam": 4,
    "destination": "",
    "callsign": "MU22"
  },
  "305158000": {
    "name": "BBC SINGAPORE",
    "type": 70,
    "length": 149,
    "beam": 23,
    "destination": "CAWND",
    "callsign": "V2HX7"
  },
  "367350360": {
    "name": "SPIRIT OF NAVY PIER",
    "type": 60,
    "length": 42,
    "beam": 10,
    "destination": "USCHI<>USCHI",
    "callsign": "WCY3193"
  },
  "316045085": {
    "name": "NORTHERN SPIRIT1",
    "type": 99,
    "length": 39,
    "beam": 9,
    "destination": "",
    "callsign": "CFI9998"
  },
  "266463000": {
    "name": "THUN VENERN",
    "type": 80,
    "length": 150,
    "beam": 23,
    "destination": "CA SNI",
    "callsign": "SGTE"
  },
  "367745090": {
    "name": "SKYVIEW",
    "type": 60,
    "length": 29,
    "beam": 10,
    "destination": "USCHI<>USCHI",
    "callsign": "WDI9084"
  },
  "538010710": {
    "name": "FEDERAL HAMILTON",
    "type": 70,
    "length": 200,
    "beam": 24,
    "destination": "CA WND",
    "callsign": "V7A7306"
  },
  "316045066": {
    "name": "MV ONGIARA",
    "type": 0,
    "length": 0,
    "beam": 0,
    "destination": "",
    "callsign": "VC 4161"
  },
  "316023808": {
    "name": "BAIE COMEAU",
    "type": 70,
    "length": 225,
    "beam": 24,
    "destination": "HAMILTON",
    "callsign": "CFN6357"
  },
  "367164050": {
    "name": "CAP STREETER",
    "type": 99,
    "length": 20,
    "beam": 7,
    "destination": "",
    "callsign": "WCX3809"
  },
  "338165341": {
    "name": "SIMPSON SHERIFF DIVE",
    "type": 99,
    "length": 14,
    "beam": 12,
    "destination": "",
    "callsign": "SIMPSON"
  },
  "367307630": {
    "name": "GIDDY UP",
    "type": 60,
    "length": 16,
    "beam": 6,
    "destination": "CHICAGO",
    "callsign": "WDD9155"
  },
  "366999978": {
    "name": "CG BRISTOL BAY",
    "type": 52,
    "length": 42,
    "beam": 11,
    "destination": "DETROIT MI",
    "callsign": "NRLY"
  },
  "316018031": {
    "name": "ALGOMA GUARDIAN",
    "type": 70,
    "length": 222,
    "beam": 23,
    "destination": "HAMILTON",
    "callsign": "CFK9698"
  },
  "367376370": {
    "name": "WYOMING",
    "type": 99,
    "length": 0,
    "beam": 0,
    "destination": "BUFFALO, NY",
    "callsign": ""
  },
  "316011710": {
    "name": "ALGOMA HARVESTER",
    "type": 70,
    "length": 225,
    "beam": 24,
    "destination": "THUNDER BAY",
    "callsign": "XJBK"
  },
  "316048071": {
    "name": "THOUSAND ISLANDER II",
    "type": 60,
    "length": 30,
    "beam": 6,
    "destination": "GANANOQUE",
    "callsign": ""
  },
  "316048073": {
    "name": "THOUSAND ISLANDER IV",
    "type": 60,
    "length": 36,
    "beam": 8,
    "destination": "GANANOQUE",
    "callsign": "VA3436"
  },
  "316001701": {
    "name": "JOHN D LEITCH",
    "type": 70,
    "length": 222,
    "beam": 24,
    "destination": "CLARKSON",
    "callsign": "VGWM"
  },
  "316002063": {
    "name": "SEA EAGLE II",
    "type": 52,
    "length": 164,
    "beam": 23,
    "destination": "DETROIT SMC ROUGE",
    "callsign": "CZ9891"
  },
  "338888000": {
    "name": "CLYDE S. VANENKEVORT",
    "type": 31,
    "length": 41,
    "beam": 15,
    "destination": "DETROIT SHORTCUT C1",
    "callsign": "WDJ4194"
  },
  "316045082": {
    "name": "MV THOMAS RENNIE",
    "type": 0,
    "length": 0,
    "beam": 0,
    "destination": "",
    "callsign": "VC4161"
  },
  "366978440": {
    "name": "MISSOURI",
    "type": 52,
    "length": 30,
    "beam": 9,
    "destination": "DULUTH/SUPERIOR",
    "callsign": "WAI9279"
  },
  "316044324": {
    "name": "ORIOLE",
    "type": 69,
    "length": 21,
    "beam": 7,
    "destination": "",
    "callsign": "CFI9997"
  },
  "316002873": {
    "name": "OCEAN GOLF",
    "type": 52,
    "length": 25,
    "beam": 10,
    "destination": "HAMILTON",
    "callsign": "FGYJ"
  },
  "316049426": {
    "name": "YANKEE LADY 3",
    "type": 60,
    "length": 35,
    "beam": 8,
    "destination": "",
    "callsign": ""
  },
  "367398450": {
    "name": "LITTLE LADY",
    "type": 60,
    "length": 21,
    "beam": 8,
    "destination": "USCHI<>US",
    "callsign": "WCZ2897"
  },
  "636024470": {
    "name": "GOLDEN PALM",
    "type": 80,
    "length": 150,
    "beam": 23,
    "destination": "CASNI",
    "callsign": "5LST6"
  },
  "369812000": {
    "name": "CAROLINE MCKEE",
    "type": 52,
    "length": 41,
    "beam": 11,
    "destination": "CLEVELAND",
    "callsign": "WDK8680"
  },
  "366988420": {
    "name": "MEREDITH ASHTON",
    "type": 52,
    "length": 33,
    "beam": 10,
    "destination": "WASHBURN",
    "callsign": "WDL5580"
  },
  "367073840": {
    "name": "JAMES J. VERSLUIS",
    "type": 52,
    "length": 0,
    "beam": 0,
    "destination": "CHICAGO",
    "callsign": "WDD9506"
  },
  "367364840": {
    "name": "SHAKE A LEG",
    "type": 60,
    "length": 17,
    "beam": 2,
    "destination": "USCHI<>USCHI",
    "callsign": "WDE5311"
  },
  "368395170": {
    "name": "NEW YORK",
    "type": 52,
    "length": 19,
    "beam": 6,
    "destination": "DETROIT",
    "callsign": "WDP8970"
  },
  "316035873": {
    "name": "ISLAND QUEEN III",
    "type": 60,
    "length": 30,
    "beam": 7,
    "destination": "",
    "callsign": "VA3412"
  },
  "316003616": {
    "name": "STORMONT",
    "type": 99,
    "length": 0,
    "beam": 0,
    "destination": "WINDSOR",
    "callsign": ""
  },
  "368351910": {
    "name": "FLOUR POWER",
    "type": 37,
    "length": 19,
    "beam": 6,
    "destination": "DULUTH MN",
    "callsign": "WDP4163"
  },
  "316003880": {
    "name": "EVERLAST",
    "type": 80,
    "length": 164,
    "beam": 22,
    "destination": "SARNIA",
    "callsign": "CFG8057"
  },
  "316013215": {
    "name": "ALGOCANADA",
    "type": 81,
    "length": 130,
    "beam": 20,
    "destination": "NANTICOKE",
    "callsign": "CFN5193"
  },
  "366947250": {
    "name": "BLUE HERON",
    "type": 90,
    "length": 27,
    "beam": 8,
    "destination": "SUPERIOR.WI",
    "callsign": "WCX7521"
  },
  "366825870": {
    "name": "BRAVO",
    "type": 0,
    "length": 15,
    "beam": 5,
    "destination": "",
    "callsign": "WDA5940"
  },
  "209016000": {
    "name": "TORRENT",
    "type": 70,
    "length": 185,
    "beam": 24,
    "destination": "CA TOR",
    "callsign": "5BWL2"
  },
  "316046951": {
    "name": "TORONTO ELITE",
    "type": 69,
    "length": 23,
    "beam": 6,
    "destination": "TORONTOON",
    "callsign": "CFA3479"
  },
  "367776910": {
    "name": "ISLAND TIME",
    "type": 99,
    "length": 0,
    "beam": 0,
    "destination": "",
    "callsign": "WDHB"
  },
  "316048477": {
    "name": "ODYSSEY TORONTO",
    "type": 99,
    "length": 46,
    "beam": 11,
    "destination": "",
    "callsign": "CHA2135"
  },
  "367531970": {
    "name": "GOTTA GO NOW",
    "type": 6,
    "length": 19,
    "beam": 5,
    "destination": "NAVY_PIER",
    "callsign": "WDG4007"
  },
  "367102450": {
    "name": "TENACIOUS",
    "type": 99,
    "length": 21,
    "beam": 8,
    "destination": "",
    "callsign": "WDC9450"
  },
  "316001096": {
    "name": "MOLLY M1",
    "type": 31,
    "length": 28,
    "beam": 8,
    "destination": "PORT WELLER",
    "callsign": "CYKB"
  },
  "303514000": {
    "name": "ALLIANCE",
    "type": 69,
    "length": 24,
    "beam": 6,
    "destination": "DETROIT",
    "callsign": "WDC8119"
  },
  "368039870": {
    "name": "ODYSSEY CHICAGO_IVER",
    "type": 60,
    "length": 43,
    "beam": 9,
    "destination": "CHICAGO",
    "callsign": "WDK2887"
  },
  "316017110": {
    "name": "ALGOMA ENDEAVOUR",
    "type": 70,
    "length": 225,
    "beam": 24,
    "destination": "THUNDER BAY",
    "callsign": "VDAC"
  },
  "316003123": {
    "name": "JIIMAAN",
    "type": 60,
    "length": 61,
    "beam": 15,
    "destination": "",
    "callsign": "CFI9556"
  },
  "338185247": {
    "name": "FISCHER HAYDEN",
    "type": 52,
    "length": 0,
    "beam": 0,
    "destination": "BUFFALO",
    "callsign": "WDA4498"
  },
  "316005377": {
    "name": "CAPE STORM",
    "type": 51,
    "length": 15,
    "beam": 5,
    "destination": "SAR PORT WELLER",
    "callsign": ""
  },
  "367043240": {
    "name": "PATRICIAHOEY",
    "type": 0,
    "length": 0,
    "beam": 0,
    "destination": "",
    "callsign": "WC4737"
  },
  "367516930": {
    "name": "MACEY LAUREN",
    "type": 50,
    "length": 22,
    "beam": 8,
    "destination": "",
    "callsign": "WDG2565"
  },
  "316048672": {
    "name": "KWASIND",
    "type": 69,
    "length": 22,
    "beam": 6,
    "destination": "",
    "callsign": "CFA5854"
  },
  "367050160": {
    "name": "BURNS HARBOR",
    "type": 70,
    "length": 304,
    "beam": 32,
    "destination": "SUPERIOR",
    "callsign": "WDC6027"
  },
  "316015050": {
    "name": "ALGOTERRA",
    "type": 82,
    "length": 144,
    "beam": 23,
    "destination": "SARNIA",
    "callsign": "VCZR"
  },
  "366938770": {
    "name": "H LEE WHITE",
    "type": 70,
    "length": 215,
    "beam": 24,
    "destination": "CLEVELAND",
    "callsign": "WZD2465"
  },
  "367360260": {
    "name": "ODYSSEY LAKE MI_IGAN",
    "type": 60,
    "length": 61,
    "beam": 12,
    "destination": "USCHI><USCHI",
    "callsign": "WBU4276"
  }
}